{
    "title": "React Google Maps - College Picker App",
    "libraries": [],
    "version": "weekly",
    "tag": "rgm_college_picker",
    "name": "rgm-college-picker",
    "pagination": {
      "data": "mode",
      "size": 1,
      "alias": "mode"
    },
    "tsx": true,
    "permalink": "samples/{{ page.fileSlug }}/{{mode}}/{% if mode == 'jsfiddle' %}demo{% else %}index{% endif %}.{{ page.outputFileExtension }}",
    "dependencies": ["@vis.gl/react-google-maps", "react", "react-dom", "vite"]
  }